LICENSE
MANIFEST.in
README
README.rst
setup.py
yt/__init__.py
yt.recipe.shell.egg-info/PKG-INFO
yt.recipe.shell.egg-info/SOURCES.txt
yt.recipe.shell.egg-info/dependency_links.txt
yt.recipe.shell.egg-info/entry_points.txt
yt.recipe.shell.egg-info/top_level.txt
yt/recipe/__init__.py
yt/recipe/shell.py
yt/recipe/shell_tests.py